tqtklib/__init__.py
tqtklib/config_manager.py
tqtklib/constants.py
tqtklib/common/__init__.py
tqtklib/common/constants.py
tqtklib/file_manager/__init__.py
tqtklib/file_manager/file_manager.py
tqtklib/file_manager/file_name_parser.py
tqtk_lib-0.1.1.dist-info/METADATA
tqtk_lib-0.1.1.dist-info/WHEEL
tqtk_lib-0.1.1.dist-info/top_level.txt
tqtk_lib-0.1.1.dist-info/RECORD
